<?xml version="1.0" encoding="UTF-8"?><record_update table="sys_sg_screen_field">
    <sys_sg_screen_field action="DELETE">
        <data_item_field_name>u_when_needed</data_item_field_name>
        <description_text/>
        <description_text_field/>
        <description_text_type/>
        <field_name/>
        <hidden>false</hidden>
        <order>400</order>
        <record_id_field/>
        <screen display_value="Details">6c01d12607e9201074c5fd1e7c1ed0e1</screen>
        <screen_data_item_table>x_58872_needit_needit</screen_data_item_table>
        <sys_class_name>sys_sg_screen_field</sys_class_name>
        <sys_created_by>admin</sys_created_by>
        <sys_created_on>2021-01-09 18:03:51</sys_created_on>
        <sys_id>977c5daa07e9201074c5fd1e7c1ed0f1</sys_id>
        <sys_mod_count>1</sys_mod_count>
        <sys_name>u_when_needed</sys_name>
        <sys_package display_value="NeedIt" source="x_58872_needit">6ead8e780f603200cd674f8ce1050ed1</sys_package>
        <sys_policy/>
        <sys_scope display_value="NeedIt">6ead8e780f603200cd674f8ce1050ed1</sys_scope>
        <sys_update_name>sys_sg_screen_field_977c5daa07e9201074c5fd1e7c1ed0f1</sys_update_name>
        <sys_updated_by>admin</sys_updated_by>
        <sys_updated_on>2021-01-09 18:17:44</sys_updated_on>
        <type>auto</type>
        <value_only>false</value_only>
    </sys_sg_screen_field>
    <sys_translated_text action="DELETE" query="documentkey=977c5daa07e9201074c5fd1e7c1ed0f1"/>
    <sys_update_version action="INSERT_OR_UPDATE">
        <action>DELETE</action>
        <application display_value="NeedIt">6ead8e780f603200cd674f8ce1050ed1</application>
        <file_path/>
        <instance_id>21aae77f4f835280facf220f0310c70c</instance_id>
        <instance_name>dev23928</instance_name>
        <name>sys_sg_screen_field_977c5daa07e9201074c5fd1e7c1ed0f1</name>
        <payload><![CDATA[<?xml version="1.0" encoding="UTF-8"?><record_update table="sys_sg_screen_field"><sys_sg_screen_field action="INSERT_OR_UPDATE"><data_item_field_name>u_when_needed</data_item_field_name><description_text/><description_text_field/><description_text_type/><field_name/><hidden>false</hidden><order>400</order><record_id_field/><screen display_value="Details">6c01d12607e9201074c5fd1e7c1ed0e1</screen><screen_data_item_table>x_58872_needit_needit</screen_data_item_table><sys_class_name>sys_sg_screen_field</sys_class_name><sys_created_by>admin</sys_created_by><sys_created_on>2021-01-09 18:03:51</sys_created_on><sys_id>977c5daa07e9201074c5fd1e7c1ed0f1</sys_id><sys_mod_count>1</sys_mod_count><sys_name>u_when_needed</sys_name><sys_package display_value="NeedIt" source="x_58872_needit">6ead8e780f603200cd674f8ce1050ed1</sys_package><sys_policy/><sys_scope display_value="NeedIt">6ead8e780f603200cd674f8ce1050ed1</sys_scope><sys_update_name>sys_sg_screen_field_977c5daa07e9201074c5fd1e7c1ed0f1</sys_update_name><sys_updated_by>admin</sys_updated_by><sys_updated_on>2021-01-09 18:17:44</sys_updated_on><type>auto</type><value_only>false</value_only></sys_sg_screen_field><sys_translated_text action="delete_multiple" query="documentkey=977c5daa07e9201074c5fd1e7c1ed0f1"/></record_update>]]></payload>
        <payload_hash>-831320972</payload_hash>
        <record_name>u_when_needed</record_name>
        <reverted_from/>
        <source>39b96976070d601074c5fd1e7c1ed0c7</source>
        <source_table>sys_update_set</source_table>
        <state>previous</state>
        <sys_created_by>admin</sys_created_by>
        <sys_created_on>2021-01-09 18:17:44</sys_created_on>
        <sys_id>3eafd56e07e9201074c5fd1e7c1ed045</sys_id>
        <sys_mod_count>0</sys_mod_count>
        <sys_recorded_at>176e85e54560000001</sys_recorded_at>
        <sys_updated_by>admin</sys_updated_by>
        <sys_updated_on>2021-01-09 18:17:44</sys_updated_on>
        <type>Screen fields</type>
        <update_guid>36afd56e27e9201006c8da54cc116745</update_guid>
        <update_guid_history>36afd56e27e9201006c8da54cc116745:-831320972,9f7c5daac6e9201010d0411c830dd5f2:-89825226</update_guid_history>
    </sys_update_version>
    <sys_metadata_delete action="INSERT_OR_UPDATE">
        <sys_audit_delete/>
        <sys_class_name>sys_metadata_delete</sys_class_name>
        <sys_created_by>admin</sys_created_by>
        <sys_created_on>2021-01-09 18:23:52</sys_created_on>
        <sys_db_object display_value="" name="sys_sg_screen_field">sys_sg_screen_field</sys_db_object>
        <sys_id>6a9129a44e964c3cb2dffecdee2d8f10</sys_id>
        <sys_metadata>977c5daa07e9201074c5fd1e7c1ed0f1</sys_metadata>
        <sys_mod_count>0</sys_mod_count>
        <sys_name>u_when_needed</sys_name>
        <sys_package display_value="NeedIt" source="x_58872_needit">6ead8e780f603200cd674f8ce1050ed1</sys_package>
        <sys_parent/>
        <sys_policy/>
        <sys_scope display_value="NeedIt">6ead8e780f603200cd674f8ce1050ed1</sys_scope>
        <sys_scope_delete display_value="">94872a8897db403e8ee69a431de2fca4</sys_scope_delete>
        <sys_update_name>sys_sg_screen_field_977c5daa07e9201074c5fd1e7c1ed0f1</sys_update_name>
        <sys_update_version display_value="sys_sg_screen_field_977c5daa07e9201074c5fd1e7c1ed0f1">3eafd56e07e9201074c5fd1e7c1ed045</sys_update_version>
        <sys_updated_by>admin</sys_updated_by>
        <sys_updated_on>2021-01-09 18:23:52</sys_updated_on>
    </sys_metadata_delete>
</record_update>
